LICENSE.txt
MANIFEST.in
README.rst
setup.py
django_shop_viveum.egg-info/PKG-INFO
django_shop_viveum.egg-info/SOURCES.txt
django_shop_viveum.egg-info/dependency_links.txt
django_shop_viveum.egg-info/not-zip-safe
django_shop_viveum.egg-info/requires.txt
django_shop_viveum.egg-info/top_level.txt
docs/ssl-problem.rst
tests/manage.py
tests/testapp/__init__.py
tests/testapp/models.py
tests/testapp/settings.py
tests/testapp/tests.py
tests/testapp/urls.py
tests/testapp/viveum_settings_sample.py
viveum/__init__.py
viveum/admin.py
viveum/context_processors.py
viveum/forms.py
viveum/models.py
viveum/offsite_backend.py
viveum/views.py
viveum/migrations/0001_initial.py
viveum/migrations/__init__.py
viveum/templates/viveum/order_form.html
viveum/templates/viveum/payment_zone.html