Metadata-Version: 1.1
Name: django-shop-viveum
Version: 0.3.3
Summary: A payment backend module for django-SHOP, using Viveum (https://viveum.v-psp.com) as PSP.
Home-page: https://github.com/jrief/django-shop-viveum
Author: Jacob Rief
Author-email: jacob.rief@gmail.com
License: BSD License
Keywords: django,django-shop,viveum
Platform: OS Independent
Classifier: Development Status :: 3 - Alpha
Classifier: Environment :: Web Environment
Classifier: Framework :: Django
Classifier: Intended Audience :: Developers
Classifier: License :: OSI Approved :: BSD License
Classifier: Operating System :: OS Independent
Classifier: Programming Language :: Python
